kerasbeats/__init__.py
kerasbeats/nbeats.py
kerasbeats/utilities.py
keras_beats-0.0.1.dist-info/LICENSE
keras_beats-0.0.1.dist-info/METADATA
keras_beats-0.0.1.dist-info/WHEEL
keras_beats-0.0.1.dist-info/top_level.txt
keras_beats-0.0.1.dist-info/RECORD
