Metadata-Version: 2.1
Name: keras-beats
Version: 0.0.1
Summary: Lightweight installation of NBeats NN architecture for keras
Home-page: https://github.com/JonathanBechtel/KerasBeats
Author: Jonathan Bechtel
Author-email: jonathan@jonathanbech.tel
License: UNKNOWN
Platform: UNKNOWN
Classifier: Programming Language :: Python :: 3
Classifier: License :: OSI Approved :: MIT License
Classifier: Operating System :: OS Independent
Requires-Python: >=3.6
License-File: LICENSE
Requires-Dist: tensorflow (>=2.0.0)
Requires-Dist: pandas
Requires-Dist: numpy
